amazon_textract_idp_cdk_constructs/__init__.py
amazon_textract_idp_cdk_constructs/py.typed
amazon_textract_idp_cdk_constructs/_jsii/__init__.py
amazon_textract_idp_cdk_constructs/_jsii/amazon-textract-idp-cdk-constructs@0.0.43.jsii.tgz
amazon_textract_idp_cdk_constructs-0.0.43.dist-info/LICENSE
amazon_textract_idp_cdk_constructs-0.0.43.dist-info/METADATA
amazon_textract_idp_cdk_constructs-0.0.43.dist-info/WHEEL
amazon_textract_idp_cdk_constructs-0.0.43.dist-info/top_level.txt
amazon_textract_idp_cdk_constructs-0.0.43.dist-info/RECORD
