Metadata-Version: 2.1
Name: amazon-textract-idp-cdk-constructs
Version: 0.0.43
Summary: amazon-textract-idp-cdk-constructs
Home-page: https://github.com/aws-samples/amazon-textract-idp-cdk-constructs.git
Author: Martin Schade<45048633+schadem@users.noreply.github.com>
License: MIT-0
Project-URL: Source, https://github.com/aws-samples/amazon-textract-idp-cdk-constructs.git
Classifier: Intended Audience :: Developers
Classifier: Operating System :: OS Independent
Classifier: Programming Language :: JavaScript
Classifier: Programming Language :: Python :: 3 :: Only
Classifier: Programming Language :: Python :: 3.8
Classifier: Programming Language :: Python :: 3.9
Classifier: Programming Language :: Python :: 3.10
Classifier: Programming Language :: Python :: 3.11
Classifier: Typing :: Typed
Classifier: Development Status :: 5 - Production/Stable
Classifier: License :: OSI Approved
Requires-Python: ~=3.8
License-File: LICENSE
Requires-Dist: aws-cdk-lib <3.0.0,>=2.135.0
Requires-Dist: constructs <11.0.0,>=10.0.5
Requires-Dist: jsii <2.0.0,>=1.96.0
Requires-Dist: publication >=0.0.3
Requires-Dist: typeguard ~=2.13.3
